{".class": "MypyFile", "_fullname": "ArduinoConnectV1", "is_partial_stub_package": false, "is_stub": false, "names": {".class": "SymbolTable", "__doc__": {".class": "SymbolTableNode", "kind": "Gdef", "node": {".class": "Var", "flags": [], "fullname": "ArduinoConnectV1.__doc__", "name": "__doc__", "type": "builtins.str"}}, "__file__": {".class": "SymbolTableNode", "kind": "Gdef", "node": {".class": "Var", "flags": [], "fullname": "ArduinoConnectV1.__file__", "name": "__file__", "type": "builtins.str"}}, "__name__": {".class": "SymbolTableNode", "kind": "Gdef", "node": {".class": "Var", "flags": [], "fullname": "ArduinoConnectV1.__name__", "name": "__name__", "type": "builtins.str"}}, "__package__": {".class": "SymbolTableNode", "kind": "Gdef", "node": {".class": "Var", "flags": [], "fullname": "ArduinoConnectV1.__package__", "name": "__package__", "type": "builtins.str"}}, "a": {".class": "SymbolTableNode", "kind": "Gdef", "node": {".class": "Var", "flags": [], "fullname": "ArduinoConnectV1.a", "name": "a", "type": {".class": "AnyType", "missing_import_name": "ArduinoConnectV1.serial", "source_any": {".class": "AnyType", "missing_import_name": "ArduinoConnectV1.serial", "source_any": null, "type_of_any": 3}, "type_of_any": 7}}}, "b": {".class": "SymbolTableNode", "kind": "Gdef", "node": {".class": "Var", "flags": [], "fullname": "ArduinoConnectV1.b", "name": "b", "type": {".class": "AnyType", "missing_import_name": "ArduinoConnectV1.serial", "source_any": {".class": "AnyType", "missing_import_name": "ArduinoConnectV1.serial", "source_any": null, "type_of_any": 3}, "type_of_any": 7}}}, "data": {".class": "SymbolTableNode", "kind": "Gdef", "node": {".class": "Var", "flags": [], "fullname": "ArduinoConnectV1.data", "name": "data", "type": {".class": "Instance", "args": ["builtins.int"], "type_ref": "builtins.list"}}}, "new_data": {".class": "SymbolTableNode", "kind": "Gdef", "node": {".class": "Var", "flags": [], "fullname": "ArduinoConnectV1.new_data", "name": "new_data", "type": {".class": "Instance", "args": [{".class": "AnyType", "missing_import_name": "ArduinoConnectV1.serial", "source_any": {".class": "AnyType", "missing_import_name": "ArduinoConnectV1.serial", "source_any": null, "type_of_any": 3}, "type_of_any": 7}], "type_ref": "builtins.list"}}}, "ser": {".class": "SymbolTableNode", "kind": "Gdef", "node": {".class": "Var", "flags": [], "fullname": "ArduinoConnectV1.ser", "name": "ser", "type": {".class": "AnyType", "missing_import_name": "ArduinoConnectV1.serial", "source_any": {".class": "AnyType", "missing_import_name": "ArduinoConnectV1.serial", "source_any": null, "type_of_any": 3}, "type_of_any": 7}}}, "serial": {".class": "SymbolTableNode", "kind": "Gdef", "node": {".class": "Var", "flags": ["is_suppressed_import"], "fullname": "ArduinoConnectV1.serial", "name": "serial", "type": {".class": "AnyType", "missing_import_name": "ArduinoConnectV1.serial", "source_any": null, "type_of_any": 3}}}, "time": {".class": "SymbolTableNode", "cross_ref": "time", "kind": "Gdef"}, "toByte": {".class": "SymbolTableNode", "kind": "Gdef", "node": {".class": "FuncDef", "arg_kinds": [0, 0], "arg_names": ["data_string", "base"], "flags": [], "fullname": "ArduinoConnectV1.toByte", "name": "toByte", "type": null}}, "values": {".class": "SymbolTableNode", "kind": "Gdef", "node": {".class": "Var", "flags": [], "fullname": "ArduinoConnectV1.values", "name": "values", "type": "builtins.bytearray"}}}, "path": "/Users/curtisbucher/Desktop/briaNIAC/Software/StormConnectPython/ArduinoConnectV1.py"}